MANIFEST.in
README.rst
bootstrap.py
buildout.cfg
setup.cfg
setup.py
collective/.DS_Store
collective/__init__.py
collective.emailconfirmationregistration.egg-info/PKG-INFO
collective.emailconfirmationregistration.egg-info/SOURCES.txt
collective.emailconfirmationregistration.egg-info/dependency_links.txt
collective.emailconfirmationregistration.egg-info/entry_points.txt
collective.emailconfirmationregistration.egg-info/namespace_packages.txt
collective.emailconfirmationregistration.egg-info/not-zip-safe
collective.emailconfirmationregistration.egg-info/requires.txt
collective.emailconfirmationregistration.egg-info/top_level.txt
collective/emailconfirmationregistration/__init__.py
collective/emailconfirmationregistration/approve.pt
collective/emailconfirmationregistration/browser.py
collective/emailconfirmationregistration/configure.zcml
collective/emailconfirmationregistration/confirm-email.pt
collective/emailconfirmationregistration/interfaces.py
collective/emailconfirmationregistration/under-review.pt
collective/emailconfirmationregistration/upgrades.py
collective/emailconfirmationregistration/profiles/default/browserlayer.xml
collective/emailconfirmationregistration/profiles/default/controlpanel.xml
collective/emailconfirmationregistration/profiles/default/metadata.xml
collective/emailconfirmationregistration/profiles/default/registry.xml
docs/HISTORY.txt
docs/INSTALL.txt
docs/LICENSE.GPL
docs/LICENSE.txt
docs/TODO.txt