Metadata-Version: 1.1
Name: collective.emailconfirmationregistration
Version: 1.2.0b3
Summary: Providing an extra verification step for Plone when self-registration is enabled
Home-page: https://github.com/collective/collective.emailconfirmationregistration
Author: Nathan Van Gheem
Author-email: vangheem@gmail.com
License: GPL
Keywords: plone customizations
Platform: UNKNOWN
Classifier: Framework :: Plone
Classifier: Programming Language :: Python
